{
  "barcode": {},
  "bookable": {
    "N": 106,
    "Y": 10
  },
  "comments": {
    "Color Coated": 8,
    "Color Coated ": 2,
    "Colored & Painted ": 2,
    "Colored & Painted  - Pickleball": 10,
    "Painted ": 4,
    "Parkour Court": 2,
    "Pickleball": 1,
    "Pump Track": 1,
    "The court is still there, but Parks does not maintain this court due to FREMP stipulations.": 1,
    "Three parts to this Bike Park: 1 - Trials area (north) 2 - Trials area (south) 3 - Dirt jump area (south)": 3,
    "Two basketball hoops with 10 foot high fences surrounding the court": 3,
    "Two parts to this Bike Park: 1 - Trials area (west) 2 - Dirt jump area (east)": 2,
    "used to be a tennis court": 1
  },
  "community": {
    "Cloverdale": 27,
    "Fleetwood": 17,
    "Guildford": 23,
    "Newton": 36,
    "South Surrey": 35,
    "Whalley": 27
  },
  "court type": {
    "Bike Park": 11,
    "Games": 42,
    "Lacrosse Box": 6,
    "Outdoor Pool": 7,
    "Skate Park": 7,
    "Tennis": 75,
    "Volleyball": 12
  },
  "description": {
    "1 Practice Tennis Half Court & Wall #2; Clayton Park, 18513 70 Ave": 1,
    "1 Practice Tennis Half Court & Wall #2; Fleetwood Park, 15802 80 Ave": 1,
    "1 Practice Tennis Half Court & Wall #2; Kennedy Park, 9058 Holt Rd": 1,
    "1 Practice Tennis Half Court & Wall #3; Fraser Heights Park, 10588 160 St": 1,
    "1 Tennis Court; Bridgeview Park, 11475 126A St": 1,
    "1 Tennis Court; Cloverdale Heights Park, 5880 Aberdeen St": 1,
    "1 Tennis Court; Douglas Park, 15044 99A Ave": 1,
    "2 Practice Tennis Half Courts & Wall #2; Maple Green Park, 8959 150 St": 2,
    "2 Practice Tennis Half Courts & Wall #3; Crescent Park School Grounds, 2440 128 St": 2,
    "2 Tennis Courts #1; Crescent Park School Grounds, 2440 128 St": 2,
    "2 Tennis Courts #1; Fleetwood Park, 15802 80 Ave": 2,
    "2 Tennis Courts #1; Fraser Heights Park, 10588 160 St": 2,
    "2 Tennis Courts #1; Maple Green Park, 8959 150 St": 2,
    "2 Tennis Courts #2; Crescent Park School Grounds, 2440 128 St": 2,
    "2 Tennis Courts; Alderwood Park, 1761 Lilac Dr": 2,
    "2 Tennis Courts; Bell Park, 1782 136 St": 2,
    "2 Tennis Courts; Bob Rutledge Park, 5424 - 148 St": 2,
    "2 Tennis Courts; Clayton Park, 18513 70 Ave": 2,
    "2 Tennis Courts; Goldstone Park, 5850 146 St": 2,
    "2 Tennis Courts; Greenaway Park, 17905 60 Ave": 2,
    "2 Tennis Courts; Hummingbird Park, 11083 Swan Cres": 2,
    "2 Tennis Courts; Meridian By The Sea Park, 2040 150 St": 2,
    "2 Tennis Courts; Morgan Creek Park, 3302 156A St": 2,
    "2 Tennis Courts; Robson Park, 12576 100 Ave": 2,
    "2 Tennis Courts; Royal Kwantlen Park, 13035 104 Ave": 2,
    "2 Tennis Courts; Sullivan Park, 6272 152 St": 2,
    "2 Tennis Courts; Sunnyside Park, 15455 26 Ave": 2,
    "4 Tennis Courts #2; Fraser Heights Park, 10588 160 St": 4,
    "4 Tennis Courts; Cloverdale Athletic Park, 6330 168 St": 4,
    "4 Tennis Courts; South Surrey Athletic Park, 1925 148 St": 4,
    "6 Tennis Courts #1; Kennedy Park, 9058 Holt Rd": 6,
    "8 Tennis Courts; Newton Athletic Park, 7395 128 St": 8,
    "Basketball Court; 110A - Games Court, 12151 Sullivan St": 1,
    "Basketball Court; Bear Creek Youth Park, 8400 King George Blvd": 1,
    "Basketball Court; Bob Rutledge Park, 5424 - 148 St": 1,
    "Basketball Court; Bridgeview Park, 11475 126A St": 1,
    "Basketball Court; Cloverdale Heights Park, 5880 Aberdeen St": 1,
    "Basketball Court; Cloverdale Youth Park Grounds, 17848 64 Ave": 1,
    "Basketball Court; Evergreen Tot-Lot - VIP Site, 15112 87B Ave": 1,
    "Basketball Court; Fleetwood Park, 15802 80 Ave": 1,
    "Basketball Court; Fraser Heights Park, 10588 160 St": 1,
    "Basketball Court; Guildford Heights Park, 10310 154 St": 1,
    "Basketball Court; Hazelgrove Park, 7080 190 St": 1,
    "Basketball Court; Hazelnut Meadows Community Park, 14069 68 Ave": 1,
    "Basketball Court; Newton Reservoir Park, 6275 128 St": 1,
    "Basketball Court; Riverside Park, 14875 108A Ave": 1,
    "Basketball Court; Robertson Drive Park, 12730 92 Ave": 1,
    "Basketball Court; Royal Kwantlen Park, 13035 104 Ave": 1,
    "Basketball Court; South Surrey Athletic Park, 1925 148 St": 1,
    "Basketball Court; Surrey Sport & Leisure Complex Grounds, 16555 Fraser Hwy": 1,
    "Basketball Court; Tamanawis Park, 12515 64 Ave": 1,
    "Basketball Court; Tom Binnie Park, 10665 City Parkway": 1,
    "Basketball Half Court #1; Holland Park, 13428 Old Yale Road": 1,
    "Basketball Half Court #1; Newton Athletic Park, 7395 128 St": 1,
    "Basketball Half Court #2; Holland Park, 13428 Old Yale Road": 1,
    "Basketball Half Court #2; Maple Green Park, 8959 150 St": 1,
    "Basketball Half Court #2; Newton Athletic Park, 7395 128 St": 1,
    "Basketball Half Court #3; Maple Green Park, 8959 150 St": 1,
    "Basketball Half Court #3; Newton Athletic Park, 7395 128 St": 1,
    "Basketball Half Court #4; Newton Athletic Park, 7395 128 St": 1,
    "Basketball Half Court; Bonaccord Park, 14962 98 Ave": 1,
    "Basketball Half Court; Holly Park, 10706 148 St": 1,
    "Basketball Half Court; Summerhill Park (Tot-Lot), 13089 Summerhill Cres": 1,
    "Basketball/Hockey Court; Alderwood Park, 1761 Lilac Dr": 1,
    "Basketball/Hockey Court; Clayton Park, 18513 70 Ave": 1,
    "Basketball/Hockey Court; Cloverdale Athletic Park, 6330 168 St": 1,
    "Basketball/Hockey Court; Don Christian Park, 6220 184 St": 1,
    "Basketball/Hockey Court; Evershine Park, 12688 70 Ave": 1,
    "Basketball/Hockey Court; Goldstone Park, 5850 146 St": 1,
    "Basketball/Hockey Court; Parkwood Village Park, 12901 73 Ave": 1,
    "Basketball/Hockey Court; Unwin Park, 13313 68 Ave": 1,
    "Bike Park; 22D - Utility ROW, 13931 100 Ave": 1,
    "Bike Park; Cloverdale Athletic Park, 6330 168 St": 2,
    "Bike Park; Fun Fun Park, 1472 - 128 St": 1,
    "Bike Park; Invergarry Park, 14400 Currie Dr": 1,
    "Bike Park; Latimer Park, 2786 192 St": 1,
    "Bike Park; Panorama Park, 12863 60 Ave": 1,
    "Bike Park; Port Kells Park, 19340 88 Ave": 1,
    "Bike Park; South Surrey Athletic Park, 1925 148 St": 3,
    "Fitness Area; Bear Creek Park, 13750 88 Ave": 1,
    "Fitness Area; Frank Hurt Park, 13828 77 Ave": 1,
    "Fitness Circuit; Crescent Park, 2585 132 St": 1,
    "Fitness Circuit; Hazelgrove Park, 7080 190 St": 1,
    "Fitness Circuit; Newton Senior Centre Grounds, 13775 70 Ave": 1,
    "Fitness Circuit; Port Kells Park, 19340 - 88 Ave": 1,
    "Hockey Court #1; Maple Green Park, 8959 150 St": 1,
    "Lacrosse Box #1; Unwin Park, 13313 68 Ave": 1,
    "Lacrosse Box #2; Unwin Park, 13313 68 Ave": 1,
    "Lacrosse Box; Cloverdale Athletic Park, 6330 168 St": 1,
    "Lacrosse Box; Holly Park, 10706 148 St": 1,
    "Lacrosse Box; Royal Kwantlen Park, 13035 104 Ave": 1,
    "Lacrosse Box; Tom Binnie Park   (Olympic Venue Site), 10665 City Parkway ": 1,
    "Outdoor Pool: Hjorth Road Park; 10275 148 St": 1,
    "Outdoor Pool; Bear Creek Park, 13750 88 Ave": 1,
    "Outdoor Pool; Greenaway Park, 17905 60 Ave": 1,
    "Outdoor Pool; Port Kells Park; 19340 88 Ave": 1,
    "Outdoor Pool; Royal Kwantlen Park, 13035 104 Ave": 1,
    "Outdoor Pool; Sunnyside Park, 15455 26 Ave": 1,
    "Outdoor Pool; Unwin Park, 13313 68 Ave": 1,
    "Planned Volleyball Court; Newton Athletic Park, 7395 128 St": 2,
    "Rubberized Running Track; Hazelgrove Park": 1,
    "Senior's Wellness Park; Francis Park, 15951 83 Ave": 1,
    "Skate Park (Chuck Bailey); Tom Binnie Park   (Olympic Venue Site), 10665 City Parkway": 1,
    "Skate Park; Bear Creek Youth Park, 8400 King George Blvd": 1,
    "Skate Park; Cloverdale Youth Park, 6240 Highway 15": 1,
    "Skate Park; Fraser Heights Park, 10588 160 St": 1,
    "Skate Park; Guildford Recreation Centre & Library Grounds, 15101 105 Ave": 1,
    "Skate Park; Royal Kwantlen Park, 13035 104 Ave": 1,
    "Skate Park; South Surrey Athletic Park, 1925 148 St": 1,
    "Skate Park; Surrey Sport & Leisure Complex Grounds, 16555 Fraser Hwy": 1,
    "Sport Court; Dufferin Park,17375 2 Ave": 1,
    "Sports Court; Cloverdale Youth Park, 6240 Highway 15": 1,
    "Tennis Courts; Hazelgrove Park, 7080 190 St": 2,
    "Track; Bear Creek Oval, 13750 88 Ave": 1,
    "Track; North Surrey Community Park, 15848 97A Ave": 1,
    "Track; South Surrey Athletic Park, 1925 148 St": 1,
    "Volleyball Court #1; Fleetwood Park, 15802 80 Ave": 1,
    "Volleyball Court #1; South Surrey Athletic Park, 1925 148 St": 1,
    "Volleyball Court #2; Fleetwood Park, 15802 80 Ave": 1,
    "Volleyball Court #2; South Surrey Athletic Park, 1925 148 St": 1,
    "Volleyball Court; Crescent Beach, 12160 Beecher St": 1,
    "Volleyball Court; Don Christian Park, 6220 184 St": 2,
    "Volleyball Court; Kettle Crescent Park, 15434 Kildare Dr": 1,
    "Volleyball Court; Strawberry Hill Park, 7676 122 St": 1,
    "Volleyball Court; T.E. Scott Elementary School Park, 6998 148 St": 1
  },
  "facilityid": {
    "1001439273": 1,
    "1001439274": 1,
    "1001439276": 1,
    "1001439277": 1,
    "1001439278": 1,
    "1001439280": 1,
    "1001439281": 1,
    "1001439282": 1,
    "1001439283": 1,
    "1001439284": 1,
    "1001439285": 1,
    "1001439286": 1,
    "1001439287": 1,
    "1001439288": 1,
    "1001439289": 1,
    "1001439290": 1,
    "1001439291": 1,
    "1001439292": 1,
    "1001439293": 1,
    "1001439294": 1,
    "1001439295": 1,
    "1001439296": 1,
    "1001439297": 1,
    "1001439298": 1,
    "1001439299": 1,
    "1001439300": 1,
    "1001439301": 1,
    "1001439302": 1,
    "1001439307": 1,
    "1001439308": 1,
    "1001439309": 1,
    "1001439310": 1,
    "1001439311": 1,
    "1001439312": 1,
    "1001439313": 1,
    "1001439314": 1,
    "1001439315": 1,
    "1001439316": 1,
    "1001439317": 1,
    "1001439318": 1,
    "1001439319": 1,
    "1001439320": 1,
    "1001439321": 1,
    "1001439322": 1,
    "1001439323": 1,
    "1001439324": 1,
    "1001439325": 1,
    "1001439326": 1,
    "1001439327": 1,
    "1001439329": 1,
    "1001439330": 1,
    "1001439331": 1,
    "1001439332": 1,
    "1001439333": 1,
    "1001439334": 1,
    "1001439335": 1,
    "1001439336": 1,
    "1001439337": 1,
    "1001439338": 1,
    "1001439339": 1,
    "1001439340": 1,
    "1001439341": 1,
    "1001439342": 1,
    "1001439343": 1,
    "1001439344": 1,
    "1001439345": 1,
    "1001439346": 1,
    "1001439347": 1,
    "1001439348": 1,
    "1001439349": 1,
    "1001439350": 1,
    "1001439351": 1,
    "1001439352": 1,
    "1001439353": 1,
    "1001439354": 1,
    "1001439355": 1,
    "1001439356": 1,
    "1001439357": 1,
    "1001439358": 1,
    "1001439359": 1,
    "1001439360": 1,
    "1001439361": 1,
    "1001439362": 1,
    "1001439363": 1,
    "1001439364": 1,
    "1001439365": 1,
    "1001439366": 1,
    "1001439367": 1,
    "1001439368": 1,
    "1001439369": 1,
    "1001439370": 1,
    "1001439371": 1,
    "1001439372": 1,
    "1001439373": 1,
    "1001439374": 1,
    "1001439375": 1,
    "1001439376": 1,
    "1001439377": 1,
    "1001439378": 1,
    "1001439379": 1,
    "1001439380": 1,
    "1001439381": 1,
    "1001439382": 1,
    "1001439383": 1,
    "1001439384": 1,
    "1001439385": 1,
    "1001439386": 1,
    "1001439387": 1,
    "1001439388": 1,
    "1001439389": 1,
    "1001439390": 1,
    "1001439391": 1,
    "1001439392": 1,
    "1001439393": 1,
    "1001439394": 1,
    "1001439395": 1,
    "1001439397": 1,
    "1001439398": 1,
    "1001439399": 1,
    "1001439400": 1,
    "1001439401": 1,
    "1001439402": 1,
    "1001439403": 1,
    "1001439404": 1,
    "1001439405": 1,
    "1001439406": 1,
    "1001439407": 1,
    "1001439408": 1,
    "1001598925": 1,
    "1001605779": 1,
    "1001605849": 1,
    "1001605850": 1,
    "1001743629": 1,
    "1001743630": 1,
    "1001751333": 1,
    "1001751812": 1,
    "1001753355": 1,
    "1001790182": 1,
    "1001790183": 1,
    "1001797013": 1,
    "1001797031": 1,
    "1001797035": 1,
    "1001797039": 1,
    "1001797054": 1,
    "1001797062": 1,
    "1001797078": 1,
    "1001799741": 1,
    "1001801881": 1,
    "1001843466": 1,
    "1001845576": 1,
    "1001873478": 1,
    "1001873480": 1,
    "1001879038": 1,
    "1001879039": 1,
    "1001885267": 1,
    "1001887822": 1,
    "1001887827": 1,
    "1001887828": 1,
    "1001887829": 1,
    "1001888734": 1,
    "1001888951": 1,
    "1001908129": 1,
    "1001908364": 1,
    "1001908367": 1,
    "1001911630": 1,
    "1001933987": 1,
    "1001934045": 1,
    "1001935124": 1,
    "1001942820": 1,
    "1001942830": 1,
    "1001953356": 1,
    "1001953358": 1
  },
  "field type": {},
  "lighting system": {
    "N": 13,
    "Y": 29
  },
  "location": {
    "1 half tennis court, immediately north of full courts": 1,
    "1 half tennis court, immediately west of full courts": 1,
    "128th Str.": 8,
    "128th Str. Entrance North of 26th Ave. - west courts": 2,
    "128th Str. Entrance-North of 26th Ave. - East courts": 2,
    "170th Str.": 1,
    "2 half tennis courts, immediately west of full courts": 2,
    "2 half tennis courts, west of full courts": 2,
    "Adjacent to 100th Ave. Parking Lot": 2,
    "Adjacent to 62A Ave. Parking Lot": 2,
    "Adjacent to tennis courts off 104 Ave": 1,
    "Bear Creek Oval": 1,
    "E Side Of Park": 6,
    "East of Caretakers Residence": 1,
    "East of Park Entrance Gates": 2,
    "East of Tennis Court": 1,
    "East of new parking lot": 2,
    "East of playground and North of Youth Centre": 1,
    "East side of Bear Creek Park parking lot": 1,
    "Entire Site": 1,
    "Fraser Hwy side of site": 1,
    "Hjorth Road Park, east of parking lot": 1,
    "N of 20 Ave at about 146 St": 1,
    "N of Cloverdale Youth Centre": 1,
    "N. End Of Park": 2,
    "N.W. Corner Of Park": 1,
    "N.W. Corner of Park": 4,
    "N.W. of Water Playground": 4,
    "NE corner of park": 2,
    "NE corner of park, on 72 Ave": 1,
    "NE corner of youth park": 1,
    "NE section of park": 1,
    "NE. Corner Of Site": 1,
    "NW Corner of park on 108 Ave": 2,
    "NW of Softball 1": 1,
    "Near Corner Of 73 Ave & Parkwood Dr.": 1,
    "Next To Playground Near Summerhill Cr.": 1,
    "North Side of Field": 1,
    "North Surrey Community Park Oval": 1,
    "North of Lifeguard Station": 1,
    "North of Playground": 1,
    "North of existing courts": 1,
    "North of playground": 1,
    "North of volleyball court #2": 1,
    "North side of Fire Hall": 1,
    "North side of parking lot": 1,
    "North side of west tennis court": 1,
    "Northwest Corner of Park": 2,
    "On top of Newton Reservoir": 1,
    "S side of parking lot near 64 Ave": 1,
    "S.E. Corner 150th Street": 2,
    "S.E. Corner of Park": 4,
    "S.E. Corner of Park-Old Yale Road": 2,
    "S.W. Corner of Park -104th Ave.": 1,
    "SE corner of track": 1,
    "SE of Playground": 1,
    "SE of playground": 1,
    "SE. Section Of Park Near 151 St": 1,
    "SW corner of park, just north of playground": 2,
    "South Surrey Athletic Park Oval": 1,
    "South of Community Hall, east of basketball court": 1,
    "South of Community Hall, west of tennis court": 1,
    "South of Existing Lacrosse Box": 1,
    "South of Rec Centre": 1,
    "South of Tennis Court": 1,
    "South of parking lot": 1,
    "South of tennis courts": 1,
    "South of volleyball court #1": 1,
    "South side of Greenaway Park": 1,
    "South side of Unwin Park by parking lot": 1,
    "South side of park": 1,
    "Upper West Side of Park": 2,
    "West 134th Str. Parking Lot": 1,
    "West of Tennis Court": 1,
    "West side of park, North of parking lot": 1,
    "Youth park - SW corner of park": 1,
    "adjacent to senior centre": 1,
    "adjacent to skate park": 1,
    "adjacent to softball 1": 1,
    "along P2": 1,
    "along west side of park": 3,
    "at 64 Ave entrance to site": 2,
    "beside practice court": 1,
    "between P4 and P5": 1,
    "east end of Southeast parking lot": 1,
    "east of parking lot 2": 4,
    "east of playground": 1,
    "east of washroom": 3,
    "east side of park": 1,
    "half-court, immediately West of Lacrosse Box": 1,
    "immediately west of Parking Lot": 1,
    "in site": 1,
    "just north of skate park and south of youth centre": 1,
    "near Youth Centre": 1,
    "north of parking lot": 1,
    "north of rec centre": 4,
    "north of rec centre, west of tennis courts": 1,
    "north of skate park": 1,
    "on 64 ave next to skate park": 1,
    "se corner of guildford recreation centre": 1,
    "south of paved parking lot": 1,
    "south of playground": 2,
    "south of rec centre": 1,
    "south of soccer fields": 2,
    "south of tennis courts": 2,
    "south side of park": 2,
    "south side of park, west of tennis courts": 1,
    "southeast corner of park, near high school, east court": 1,
    "southeast corner of park, near high school, west court": 1,
    "west side of park": 2,
    "west side of park, at 168 St and 63 Ave": 4,
    "within park": 1,
    "within plaza expansion NW corner of Park": 2
  },
  "maintenance responsibility": {
    "PARKS": 91,
    "Parks": 68,
    "Unknown": 1
  },
  "operational responsibility": {
    "PARKS": 88,
    "Parks": 66,
    "School District #36": 6
  },
  "outdoor rec fac type2": {
    "Bike Park": 11,
    "Courts": 135,
    "Fitness Circuit": 7,
    "Pool": 7,
    "Skate Park": 8,
    "Track": 4
  },
  "park": {
    "110A - Games Court": 1,
    "22D - Utility ROW": 1,
    "Alderwood Park": 3,
    "Bear Creek Park": 3,
    "Bear Creek Youth Park": 2,
    "Bell Park": 2,
    "Bob Rutledge Park": 3,
    "Bonaccord Park": 1,
    "Bridgeview Park": 2,
    "Clayton Park": 4,
    "Cloverdale Athletic Park": 8,
    "Cloverdale Heights Park": 2,
    "Cloverdale Youth Park": 3,
    "Crescent Beach": 1,
    "Crescent Park": 1,
    "Crescent Park School Grounds": 6,
    "Don Christian Park": 3,
    "Douglas Park": 1,
    "Dufferin Park": 1,
    "Evergreen Tot-lot": 1,
    "Evershine Park": 1,
    "Fleetwood Park": 6,
    "Francis Park": 1,
    "Frank Hurt Park": 1,
    "Fraser Heights Park": 9,
    "Fun Fun Park": 1,
    "Goldstone Park": 3,
    "Greenaway Park": 3,
    "Guildford Heights Park": 1,
    "Guildford Recreation Centre & Library Grounds": 1,
    "Hazelgrove Park": 5,
    "Hazelnut Meadows Community Park": 1,
    "Hjorth Road Park": 1,
    "Holland Park": 2,
    "Holly Park": 2,
    "Hummingbird Park": 2,
    "Invergarry Park": 1,
    "Kennedy Park": 7,
    "Kettle Crescent Park": 1,
    "Latimer Lake Park": 1,
    "Maple Green Park": 7,
    "Meridian by the Sea Park": 2,
    "Morgan Creek Park": 2,
    "Newton Athletic Park": 14,
    "Newton Reservoir Park": 1,
    "Newton Senior Centre Grounds": 1,
    "North Surrey Community Park": 1,
    "Panorama Park": 1,
    "Parkwood Village Park": 1,
    "Port Kells Park": 3,
    "Riverside Park": 1,
    "Robertson Drive Park": 1,
    "Robson Park": 2,
    "Royal Kwantlen Park": 6,
    "South Surrey Athletic Park": 12,
    "Strawberry Hill Park": 1,
    "Sullivan Park": 2,
    "Summerhill Park": 1,
    "Sunnyside Park": 3,
    "Surrey Sport & Leisure Complex Grounds": 2,
    "T.E. Scott Elementary School Park": 1,
    "Tamanawis Park": 1,
    "Tom Binnie Park": 3,
    "Unwin Park": 4
  },
  "park ownership": {},
  "primary use": {
    "Basketball": 22,
    "Basketball - Half": 11,
    "Basketball/Hockey": 8,
    "Bicycle - Dirt Jumps": 5,
    "Bicycle - Trials": 6,
    "Hockey": 1,
    "Lacrosse": 6,
    "Outdoor Pool": 7,
    "Skateboard": 8,
    "Tennis": 68,
    "Tennis - Half": 7,
    "Volleyball": 12
  },
  "reference no": {
    "1": 66,
    "1-1": 17,
    "1-1 - lit": 4,
    "1-1-1 - lit": 1,
    "1-1-2 - lit": 1,
    "1-1-3 - lit": 1,
    "1-1-4 - lit": 1,
    "1-1-5 - lit": 1,
    "1-1-6 - lit": 1,
    "1-1-7 - lit": 1,
    "1-1-8 - lit": 1,
    "1-2": 17,
    "1-2 - lit": 4,
    "1-3": 1,
    "1-3 - lit": 2,
    "1-4": 1,
    "1-4 - lit": 2,
    "1-5 - lit": 1,
    "1-6 - lit": 1,
    "2": 14,
    "2 - lit": 1,
    "2-1": 2,
    "2-1 - lit": 1,
    "2-2": 2,
    "2-2 - lit": 1,
    "2-3": 1,
    "2-4": 1,
    "3": 5,
    "3-1": 2,
    "3-2": 1,
    "4": 1
  },
  "service level": {},
  "status": {
    "OPERATING": 172
  },
  "status date": {
    "20000927134200.0": 1,
    "20010207103300.0": 1,
    "20010207103900.0": 1,
    "20010308161800.0": 1,
    "20010626074200.0": 1,
    "20020403075700.0": 1,
    "20020611131100.0": 2,
    "20020613095600.0": 2,
    "20020613100300.0": 1,
    "20020613100900.0": 1,
    "20020904134600.0": 1,
    "20021030111100.0": 1,
    "20030311111400.0": 1,
    "20030711081100.0": 1,
    "20031002140900.0": 2,
    "20031112132100.0": 1,
    "20031112132200.0": 1,
    "20040319082500.0": 1,
    "20040319082600.0": 1,
    "20040319154200.0": 1,
    "20041112080000.0": 1,
    "20061123120300.0": 1,
    "20070514154500.0": 1,
    "20070514154800.0": 1,
    "20080805164900.0": 1,
    "20080805165100.0": 2,
    "20091015144500.0": 4,
    "20091015151900.0": 1,
    "20091026082500.0": 1,
    "20100126155800.0": 2,
    "20100819105200.0": 3,
    "20101022135100.0": 1,
    "20101112150200.0": 1,
    "20101201151200.0": 4,
    "20110602111400.0": 1,
    "20110804141500.0": 2
  },
  "surface treatment": {},
  "surface type": {
    "ASPHALT": 12,
    "Asphalt": 91,
    "Concrete": 3,
    "Dirt": 11,
    "Other": 24,
    "Sand": 6
  },
  "work assignment": {}
}